setup.py
lauteur/__init__.py
lauteur/main.py
lauteur/util.py
lauteur.egg-info/PKG-INFO
lauteur.egg-info/SOURCES.txt
lauteur.egg-info/dependency_links.txt
lauteur.egg-info/namespace_packages.txt
lauteur.egg-info/not-zip-safe
lauteur.egg-info/requires.txt
lauteur.egg-info/top_level.txt