Metadata-Version: 1.1
Name: lauteur
Version: 0.0.4
Summary: Tools for ascribing authorship - to the chagrin of Barthes
Home-page: http://github.com/newslynx/lauteur
Author: Brian Abelson
Author-email: brian@newslynx.org
License: MIT
Platform: UNKNOWN
Classifier: Development Status :: 3 - Alpha
Classifier: Intended Audience :: Developers
Classifier: License :: OSI Approved :: MIT License
Classifier: Operating System :: OS Independent
Classifier: Programming Language :: Python
